pywifi/__init__.py
pywifi/_wifiutil_linux.py
pywifi/_wifiutil_win.py
pywifi/const.py
pywifi/iface.py
pywifi/profile.py
pywifi/wifi.py
pywifimotius-1.2.dist-info/METADATA
pywifimotius-1.2.dist-info/RECORD
pywifimotius-1.2.dist-info/WHEEL
pywifimotius-1.2.dist-info/top_level.txt
tests/__init__.py
tests/pywifi_test.py
